{
  "tags": null,
  "mode": 0,
  "id": "node",
  "uniqueId": 3,
  "name": "node",
  "checkReadyOnEveryCall": false,
  "checkReadyOnlyOnce": false,
  "state": "",
  "alpha": 1,
  "backFaceCulling": true,
  "sideOrientation": 1,
  "alphaMode": 2,
  "_needDepthPrePass": false,
  "disableDepthWrite": false,
  "disableColorWrite": false,
  "forceDepthWrite": false,
  "depthFunction": 0,
  "separateCullingPass": false,
  "fogEnabled": true,
  "pointSize": 1,
  "zOffset": 0,
  "pointsCloud": false,
  "fillMode": 0,
  "editorData": {
    "locations": [
      {
        "blockId": 391792,
        "x": 220,
        "y": -200
      },
      {
        "blockId": 391793,
        "x": -20,
        "y": -220
      },
      {
        "blockId": 391794,
        "x": -280,
        "y": -280
      },
      {
        "blockId": 391795,
        "x": -520,
        "y": -320
      },
      {
        "blockId": 391796,
        "x": -520,
        "y": -200
      },
      {
        "blockId": 391797,
        "x": -280,
        "y": -140
      },
      {
        "blockId": 391798,
        "x": 1940,
        "y": 940
      },
      {
        "blockId": 391799,
        "x": 1580,
        "y": 900
      },
      {
        "blockId": 391800,
        "x": 1580,
        "y": 1000
      },
      {
        "blockId": 391801,
        "x": 1200,
        "y": 760
      },
      {
        "blockId": 391802,
        "x": 160,
        "y": 520
      },
      {
        "blockId": 391803,
        "x": -200,
        "y": 220
      },
      {
        "blockId": 391804,
        "x": -480,
        "y": 180
      },
      {
        "blockId": 391805,
        "x": -3100,
        "y": 840
      },
      {
        "blockId": 391806,
        "x": -3360,
        "y": 780
      },
      {
        "blockId": 391807,
        "x": -3640,
        "y": 760
      },
      {
        "blockId": 391808,
        "x": -3920,
        "y": 720
      },
      {
        "blockId": 391809,
        "x": -4240,
        "y": 920
      },
      {
        "blockId": 391810,
        "x": -4540,
        "y": 960
      },
      {
        "blockId": 391811,
        "x": -4840,
        "y": 740
      },
      {
        "blockId": 391812,
        "x": -5120,
        "y": 780
      },
      {
        "blockId": 391813,
        "x": -4840,
        "y": 960
      },
      {
        "blockId": 391814,
        "x": -4540,
        "y": 860
      },
      {
        "blockId": 391815,
        "x": -4240,
        "y": 780
      },
      {
        "blockId": 391816,
        "x": -4540,
        "y": 740
      },
      {
        "blockId": 391817,
        "x": -3920,
        "y": 860
      },
      {
        "blockId": 391818,
        "x": -3640,
        "y": 880
      },
      {
        "blockId": 391819,
        "x": -480,
        "y": 400
      },
      {
        "blockId": 391820,
        "x": -740,
        "y": 360
      },
      {
        "blockId": 391821,
        "x": -740,
        "y": 460
      },
      {
        "blockId": 391822,
        "x": -480,
        "y": 540
      },
      {
        "blockId": 391823,
        "x": -200,
        "y": 600
      },
      {
        "blockId": 391824,
        "x": -620,
        "y": 1180
      },
      {
        "blockId": 391825,
        "x": 640,
        "y": 1100
      },
      {
        "blockId": 391826,
        "x": 360,
        "y": 1020
      },
      {
        "blockId": 391827,
        "x": 100,
        "y": 1020
      },
      {
        "blockId": 391828,
        "x": -260,
        "y": 960
      },
      {
        "blockId": 391829,
        "x": -3100,
        "y": 980
      },
      {
        "blockId": 391830,
        "x": -3640,
        "y": 980
      },
      {
        "blockId": 391831,
        "x": -3920,
        "y": 960
      },
      {
        "blockId": 391832,
        "x": -620,
        "y": 1040
      },
      {
        "blockId": 391833,
        "x": -920,
        "y": 1040
      },
      {
        "blockId": 391834,
        "x": -920,
        "y": 1300
      },
      {
        "blockId": 391835,
        "x": -260,
        "y": 1100
      },
      {
        "blockId": 391836,
        "x": 100,
        "y": 1240
      },
      {
        "blockId": 391837,
        "x": -260,
        "y": 1220
      },
      {
        "blockId": 391838,
        "x": 680,
        "y": 1780
      },
      {
        "blockId": 391839,
        "x": 340,
        "y": 1700
      },
      {
        "blockId": 391840,
        "x": 340,
        "y": 1800
      },
      {
        "blockId": 391841,
        "x": -320,
        "y": 1800
      },
      {
        "blockId": 391842,
        "x": -620,
        "y": 1800
      },
      {
        "blockId": 391843,
        "x": -940,
        "y": 1680
      },
      {
        "blockId": 391844,
        "x": -940,
        "y": 1900
      },
      {
        "blockId": 391845,
        "x": -320,
        "y": 1900
      },
      {
        "blockId": 391846,
        "x": 80,
        "y": 1920
      },
      {
        "blockId": 391847,
        "x": -320,
        "y": 2000
      },
      {
        "blockId": 391848,
        "x": 340,
        "y": 1960
      },
      {
        "blockId": 392081,
        "x": -2540,
        "y": 200
      },
      {
        "blockId": 392318,
        "x": -2800,
        "y": 140
      },
      {
        "blockId": 393039,
        "x": -2260,
        "y": 320
      },
      {
        "blockId": 393284,
        "x": -2540,
        "y": 340
      },
      {
        "blockId": 393533,
        "x": -2260,
        "y": 160
      },
      {
        "blockId": 393786,
        "x": -1980,
        "y": 320
      },
      {
        "blockId": 393787,
        "x": -1980,
        "y": 100
      },
      {
        "blockId": 394308,
        "x": -1980,
        "y": 200
      },
      {
        "blockId": 394309,
        "x": -1700,
        "y": 120
      },
      {
        "blockId": 394310,
        "x": -1440,
        "y": 180
      }
    ],
    "zoom": 0.44909815927743624,
    "x": 2293.067266193037,
    "y": 344.8057703032691,
    "frames": [
      {
        "x": -600,
        "y": -400,
        "width": 1096.77,
        "height": 440,
        "color": [
          0.2823529411764706,
          0.2823529411764706,
          0.2823529411764706
        ],
        "name": "Vertex",
        "isCollapsed": false,
        "blocks": [
          391795,
          391796,
          391794,
          391797,
          391793,
          391792
        ]
      },
      {
        "x": -1040,
        "y": 840,
        "width": 1982.56,
        "height": 600,
        "color": [
          0.2823529411764706,
          0.2823529411764706,
          0.2823529411764706
        ],
        "name": "Ring",
        "isCollapsed": false,
        "blocks": [
          391827,
          391836,
          391833,
          391824,
          391834,
          391835,
          391837,
          391832,
          391826,
          391825,
          391828
        ]
      },
      {
        "x": -860,
        "y": 120,
        "width": 1354.23,
        "height": 640,
        "color": [
          0.2823529411764706,
          0.2823529411764706,
          0.2823529411764706
        ],
        "name": "Circular Mask",
        "isCollapsed": false,
        "blocks": [
          391802,
          391822,
          391823,
          391819,
          391804,
          391803,
          391821,
          391820
        ]
      },
      {
        "x": -5200,
        "y": 620,
        "width": 2519.18,
        "height": 600,
        "color": [
          0.2823529411764706,
          0.2823529411764706,
          0.2823529411764706
        ],
        "name": "Polar Coordinates",
        "isCollapsed": false,
        "blocks": [
          391812,
          391811,
          391808,
          391816,
          391813,
          391815,
          391814,
          391810,
          391809,
          391807,
          391817,
          391806,
          391805,
          391818,
          391829,
          391830,
          391831
        ]
      },
      {
        "x": -1060,
        "y": 1560,
        "width": 2025.58,
        "height": 600,
        "color": [
          0.2823529411764706,
          0.2823529411764706,
          0.2823529411764706
        ],
        "name": "Dash",
        "isCollapsed": false,
        "blocks": [
          391842,
          391844,
          391841,
          391840,
          391845,
          391846,
          391848,
          391839,
          391838,
          391843,
          391847
        ]
      },
      {
        "x": -2960,
        "y": 0,
        "width": 1841.41,
        "height": 521.756,
        "color": [
          0.2823529411764706,
          0.2823529411764706,
          0.2823529411764706
        ],
        "name": "Rotate Mask",
        "isCollapsed": false,
        "blocks": [
          392081,
          392318,
          393039,
          393284,
          393533,
          393786,
          393787,
          394308,
          394309,
          394310
        ]
      }
    ]
  },
  "customType": "BABYLON.NodeMaterial",
  "outputNodes": [
    391792,
    391798
  ],
  "blocks": [
    {
      "customType": "BABYLON.VertexOutputBlock",
      "id": 391792,
      "name": "VertexOutput",
      "comments": "",
      "inputs": [
        {
          "name": "vector",
          "inputName": "vector",
          "targetBlockId": 391793,
          "targetConnectionName": "output"
        }
      ],
      "outputs": []
    },
    {
      "customType": "BABYLON.TransformBlock",
      "id": 391793,
      "name": "WorldPos * ViewProjectionTransform",
      "comments": "",
      "inputs": [
        {
          "name": "vector",
          "inputName": "vector",
          "targetBlockId": 391794,
          "targetConnectionName": "output"
        },
        {
          "name": "transform",
          "inputName": "transform",
          "targetBlockId": 391797,
          "targetConnectionName": "output"
        }
      ],
      "outputs": [
        {
          "name": "output"
        },
        {
          "name": "xyz"
        }
      ],
      "complementZ": 0,
      "complementW": 1
    },
    {
      "customType": "BABYLON.TransformBlock",
      "id": 391794,
      "name": "WorldPos",
      "comments": "",
      "inputs": [
        {
          "name": "vector",
          "inputName": "vector",
          "targetBlockId": 391795,
          "targetConnectionName": "output"
        },
        {
          "name": "transform",
          "inputName": "transform",
          "targetBlockId": 391796,
          "targetConnectionName": "output"
        }
      ],
      "outputs": [
        {
          "name": "output"
        },
        {
          "name": "xyz"
        }
      ],
      "complementZ": 0,
      "complementW": 1
    },
    {
      "customType": "BABYLON.InputBlock",
      "id": 391795,
      "name": "position",
      "comments": "",
      "inputs": [],
      "outputs": [
        {
          "name": "output"
        }
      ],
      "type": 8,
      "mode": 1,
      "animationType": 0,
      "visibleInInspector": false,
      "min": 0,
      "max": 0,
      "isBoolean": false,
      "matrixMode": 0,
      "isConstant": false,
      "groupInInspector": ""
    },
    {
      "customType": "BABYLON.InputBlock",
      "id": 391796,
      "name": "World",
      "comments": "",
      "inputs": [],
      "outputs": [
        {
          "name": "output"
        }
      ],
      "type": 128,
      "mode": 0,
      "systemValue": 1,
      "animationType": 0,
      "visibleInInspector": false,
      "min": 0,
      "max": 0,
      "isBoolean": false,
      "matrixMode": 0,
      "isConstant": false,
      "groupInInspector": ""
    },
    {
      "customType": "BABYLON.InputBlock",
      "id": 391797,
      "name": "ViewProjection",
      "comments": "",
      "inputs": [],
      "outputs": [
        {
          "name": "output"
        }
      ],
      "type": 128,
      "mode": 0,
      "systemValue": 4,
      "animationType": 0,
      "visibleInInspector": false,
      "min": 0,
      "max": 0,
      "isBoolean": false,
      "matrixMode": 0,
      "isConstant": false,
      "groupInInspector": ""
    },
    {
      "customType": "BABYLON.FragmentOutputBlock",
      "id": 391798,
      "name": "FragmentOutput",
      "comments": "",
      "inputs": [
        {
          "name": "rgba"
        },
        {
          "name": "rgb",
          "inputName": "rgb",
          "targetBlockId": 391799,
          "targetConnectionName": "output"
        },
        {
          "name": "a",
          "inputName": "a",
          "targetBlockId": 391800,
          "targetConnectionName": "output"
        }
      ],
      "outputs": []
    },
    {
      "customType": "BABYLON.InputBlock",
      "id": 391799,
      "name": "ringColor",
      "comments": "",
      "inputs": [],
      "outputs": [
        {
          "name": "output"
        }
      ],
      "type": 32,
      "mode": 0,
      "animationType": 0,
      "visibleInInspector": true,
      "min": 0,
      "max": 0,
      "isBoolean": false,
      "matrixMode": 0,
      "isConstant": false,
      "groupInInspector": "stroke",
      "valueType": "BABYLON.Color3",
      "value": [
        0.19607843137254902,
        0.4,
        0.5333333333333333
      ]
    },
    {
      "customType": "BABYLON.MultiplyBlock",
      "id": 391800,
      "name": "multiplyDash",
      "comments": "",
      "inputs": [
        {
          "name": "left",
          "inputName": "left",
          "targetBlockId": 391801,
          "targetConnectionName": "output"
        },
        {
          "name": "right",
          "inputName": "right",
          "targetBlockId": 391838,
          "targetConnectionName": "output"
        }
      ],
      "outputs": [
        {
          "name": "output"
        }
      ]
    },
    {
      "customType": "BABYLON.MultiplyBlock",
      "id": 391801,
      "name": "ringXcircle",
      "comments": "",
      "inputs": [
        {
          "name": "left",
          "inputName": "left",
          "targetBlockId": 391802,
          "targetConnectionName": "output"
        },
        {
          "name": "right",
          "inputName": "right",
          "targetBlockId": 391825,
          "targetConnectionName": "output"
        }
      ],
      "outputs": [
        {
          "name": "output"
        }
      ]
    },
    {
      "customType": "BABYLON.SmoothStepBlock",
      "id": 391802,
      "name": "Smooth step",
      "comments": "",
      "inputs": [
        {
          "name": "value",
          "inputName": "value",
          "targetBlockId": 391803,
          "targetConnectionName": "output"
        },
        {
          "name": "edge0",
          "inputName": "edge0",
          "targetBlockId": 391822,
          "targetConnectionName": "output"
        },
        {
          "name": "edge1",
          "inputName": "edge1",
          "targetBlockId": 391823,
          "targetConnectionName": "output"
        }
      ],
      "outputs": [
        {
          "name": "output"
        }
      ]
    },
    {
      "customType": "BABYLON.LerpBlock",
      "id": 391803,
      "name": "Lerp",
      "comments": "",
      "inputs": [
        {
          "name": "left",
          "inputName": "left",
          "targetBlockId": 391804,
          "targetConnectionName": "output"
        },
        {
          "name": "right",
          "inputName": "right",
          "targetBlockId": 394310,
          "targetConnectionName": "output"
        },
        {
          "name": "gradient",
          "inputName": "gradient",
          "targetBlockId": 391819,
          "targetConnectionName": "output"
        }
      ],
      "outputs": [
        {
          "name": "output"
        }
      ]
    },
    {
      "customType": "BABYLON.OneMinusBlock",
      "id": 391804,
      "name": "One minus",
      "comments": "",
      "inputs": [
        {
          "name": "input",
          "inputName": "input",
          "targetBlockId": 394310,
          "targetConnectionName": "output"
        }
      ],
      "outputs": [
        {
          "name": "output"
        }
      ]
    },
    {
      "customType": "BABYLON.AddBlock",
      "id": 394310,
      "name": "Add",
      "comments": "",
      "inputs": [
        {
          "name": "left",
          "inputName": "left",
          "targetBlockId": 394309,
          "targetConnectionName": "output"
        },
        {
          "name": "right",
          "inputName": "right",
          "targetBlockId": 394308,
          "targetConnectionName": "output"
        }
      ],
      "outputs": [
        {
          "name": "output"
        }
      ]
    },
    {
      "customType": "BABYLON.MultiplyBlock",
      "id": 394309,
      "name": "Multiply",
      "comments": "",
      "inputs": [
        {
          "name": "left",
          "inputName": "left",
          "targetBlockId": 393787,
          "targetConnectionName": "output"
        },
        {
          "name": "right",
          "inputName": "right",
          "targetBlockId": 393786,
          "targetConnectionName": "output"
        }
      ],
      "outputs": [
        {
          "name": "output"
        }
      ]
    },
    {
      "customType": "BABYLON.OneMinusBlock",
      "id": 393787,
      "name": "One minus",
      "comments": "",
      "inputs": [
        {
          "name": "input",
          "inputName": "input",
          "targetBlockId": 393533,
          "targetConnectionName": "output"
        }
      ],
      "outputs": [
        {
          "name": "output"
        }
      ]
    },
    {
      "customType": "BABYLON.TrigonometryBlock",
      "id": 393533,
      "name": "Abs",
      "comments": "",
      "inputs": [
        {
          "name": "input",
          "inputName": "input",
          "targetBlockId": 392081,
          "targetConnectionName": "output"
        }
      ],
      "outputs": [
        {
          "name": "output"
        }
      ],
      "operation": 2
    },
    {
      "customType": "BABYLON.SubtractBlock",
      "id": 392081,
      "name": "Subtract",
      "comments": "",
      "inputs": [
        {
          "name": "left",
          "inputName": "left",
          "targetBlockId": 391805,
          "targetConnectionName": "output"
        },
        {
          "name": "right",
          "inputName": "right",
          "targetBlockId": 392318,
          "targetConnectionName": "output"
        }
      ],
      "outputs": [
        {
          "name": "output"
        }
      ]
    },
    {
      "customType": "BABYLON.AddBlock",
      "id": 391805,
      "name": "polar_x",
      "comments": "polar coordinates X",
      "inputs": [
        {
          "name": "left",
          "displayName": "left",
          "inputName": "left",
          "targetBlockId": 391806,
          "targetConnectionName": "output"
        },
        {
          "name": "right",
          "displayName": "right",
          "inputName": "right",
          "targetBlockId": 391818,
          "targetConnectionName": "output"
        }
      ],
      "outputs": [
        {
          "name": "output",
          "displayName": "polar_x"
        }
      ]
    },
    {
      "customType": "BABYLON.MultiplyBlock",
      "id": 391806,
      "name": "Multiply",
      "comments": "",
      "inputs": [
        {
          "name": "left",
          "displayName": "left",
          "inputName": "left",
          "targetBlockId": 391807,
          "targetConnectionName": "output"
        },
        {
          "name": "right",
          "displayName": "right",
          "inputName": "right",
          "targetBlockId": 391818,
          "targetConnectionName": "output"
        }
      ],
      "outputs": [
        {
          "name": "output",
          "displayName": "output"
        }
      ]
    },
    {
      "customType": "BABYLON.DivideBlock",
      "id": 391807,
      "name": "Divide",
      "comments": "",
      "inputs": [
        {
          "name": "left",
          "displayName": "left",
          "inputName": "left",
          "targetBlockId": 391808,
          "targetConnectionName": "output"
        },
        {
          "name": "right",
          "displayName": "right",
          "inputName": "right",
          "targetBlockId": 391817,
          "targetConnectionName": "output"
        }
      ],
      "outputs": [
        {
          "name": "output",
          "displayName": "output"
        }
      ]
    },
    {
      "customType": "BABYLON.ArcTan2Block",
      "id": 391808,
      "name": "ArcTan2",
      "comments": "",
      "inputs": [
        {
          "name": "x",
          "displayName": "x",
          "inputName": "x",
          "targetBlockId": 391809,
          "targetConnectionName": "output"
        },
        {
          "name": "y",
          "displayName": "y",
          "inputName": "y",
          "targetBlockId": 391815,
          "targetConnectionName": "output"
        }
      ],
      "outputs": [
        {
          "name": "output",
          "displayName": "output"
        }
      ]
    },
    {
      "customType": "BABYLON.SubtractBlock",
      "id": 391809,
      "name": "Subtract",
      "comments": "remap Y to -1 to 1",
      "inputs": [
        {
          "name": "left",
          "displayName": "left",
          "inputName": "left",
          "targetBlockId": 391810,
          "targetConnectionName": "output"
        },
        {
          "name": "right",
          "displayName": "right",
          "inputName": "right",
          "targetBlockId": 391814,
          "targetConnectionName": "output"
        }
      ],
      "outputs": [
        {
          "name": "output",
          "displayName": "output"
        }
      ]
    },
    {
      "customType": "BABYLON.MultiplyBlock",
      "id": 391810,
      "name": "Multiply",
      "comments": "",
      "inputs": [
        {
          "name": "left",
          "displayName": "left",
          "inputName": "left",
          "targetBlockId": 391811,
          "targetConnectionName": "y"
        },
        {
          "name": "right",
          "displayName": "right",
          "inputName": "right",
          "targetBlockId": 391813,
          "targetConnectionName": "output"
        }
      ],
      "outputs": [
        {
          "name": "output",
          "displayName": "output"
        }
      ]
    },
    {
      "customType": "BABYLON.VectorSplitterBlock",
      "id": 391811,
      "name": "VectorSplitter",
      "comments": "",
      "inputs": [
        {
          "name": "xyzw",
          "displayName": "xyzw"
        },
        {
          "name": "xyz ",
          "displayName": "xyz "
        },
        {
          "name": "xy ",
          "displayName": "xy ",
          "inputName": "xy ",
          "targetBlockId": 391812,
          "targetConnectionName": "output"
        }
      ],
      "outputs": [
        {
          "name": "xyz",
          "displayName": "xyz"
        },
        {
          "name": "xy",
          "displayName": "xy"
        },
        {
          "name": "x",
          "displayName": "x"
        },
        {
          "name": "y",
          "displayName": "y"
        },
        {
          "name": "z",
          "displayName": "z"
        },
        {
          "name": "w",
          "displayName": "w"
        }
      ]
    },
    {
      "customType": "BABYLON.InputBlock",
      "id": 391812,
      "name": "uv",
      "comments": "",
      "inputs": [],
      "outputs": [
        {
          "name": "output"
        }
      ],
      "type": 4,
      "mode": 1,
      "animationType": 0,
      "visibleInInspector": false,
      "min": 0,
      "max": 0,
      "isBoolean": false,
      "matrixMode": 0,
      "isConstant": false,
      "groupInInspector": ""
    },
    {
      "customType": "BABYLON.InputBlock",
      "id": 391813,
      "name": "two",
      "comments": "",
      "inputs": [],
      "outputs": [
        {
          "name": "output"
        }
      ],
      "type": 1,
      "mode": 0,
      "animationType": 0,
      "visibleInInspector": false,
      "min": 0,
      "max": 0,
      "isBoolean": false,
      "matrixMode": 0,
      "isConstant": true,
      "groupInInspector": "",
      "valueType": "number",
      "value": 2
    },
    {
      "customType": "BABYLON.InputBlock",
      "id": 391814,
      "name": "one",
      "comments": "",
      "inputs": [],
      "outputs": [
        {
          "name": "output"
        }
      ],
      "type": 1,
      "mode": 0,
      "animationType": 0,
      "visibleInInspector": false,
      "min": 0,
      "max": 0,
      "isBoolean": false,
      "matrixMode": 0,
      "isConstant": true,
      "groupInInspector": "",
      "valueType": "number",
      "value": 1
    },
    {
      "customType": "BABYLON.SubtractBlock",
      "id": 391815,
      "name": "Subtract",
      "comments": "remap X to -1 to 1",
      "inputs": [
        {
          "name": "left",
          "displayName": "left",
          "inputName": "left",
          "targetBlockId": 391816,
          "targetConnectionName": "output"
        },
        {
          "name": "right",
          "displayName": "right",
          "inputName": "right",
          "targetBlockId": 391814,
          "targetConnectionName": "output"
        }
      ],
      "outputs": [
        {
          "name": "output",
          "displayName": "output"
        }
      ]
    },
    {
      "customType": "BABYLON.MultiplyBlock",
      "id": 391816,
      "name": "Multiply",
      "comments": "",
      "inputs": [
        {
          "name": "left",
          "displayName": "left",
          "inputName": "left",
          "targetBlockId": 391811,
          "targetConnectionName": "x"
        },
        {
          "name": "right",
          "displayName": "right",
          "inputName": "right",
          "targetBlockId": 391813,
          "targetConnectionName": "output"
        }
      ],
      "outputs": [
        {
          "name": "output",
          "displayName": "output"
        }
      ]
    },
    {
      "customType": "BABYLON.InputBlock",
      "id": 391817,
      "name": "Pi",
      "comments": "",
      "inputs": [],
      "outputs": [
        {
          "name": "output"
        }
      ],
      "type": 1,
      "mode": 0,
      "animationType": 0,
      "visibleInInspector": false,
      "min": 0,
      "max": 0,
      "isBoolean": false,
      "matrixMode": 0,
      "isConstant": true,
      "groupInInspector": "",
      "valueType": "number",
      "value": 3.14
    },
    {
      "customType": "BABYLON.InputBlock",
      "id": 391818,
      "name": "half",
      "comments": "",
      "inputs": [],
      "outputs": [
        {
          "name": "output"
        }
      ],
      "type": 1,
      "mode": 0,
      "animationType": 0,
      "visibleInInspector": false,
      "min": 0,
      "max": 0,
      "isBoolean": false,
      "matrixMode": 0,
      "isConstant": true,
      "groupInInspector": "",
      "valueType": "number",
      "value": 0.5
    },
    {
      "customType": "BABYLON.InputBlock",
      "id": 392318,
      "name": "maskRotation",
      "comments": "",
      "inputs": [],
      "outputs": [
        {
          "name": "output"
        }
      ],
      "type": 1,
      "mode": 0,
      "systemValue": null,
      "animationType": 0,
      "visibleInInspector": true,
      "min": 0,
      "max": 1,
      "isBoolean": false,
      "matrixMode": 0,
      "isConstant": false,
      "groupInInspector": "mask",
      "valueType": "number",
      "value": 0
    },
    {
      "customType": "BABYLON.OneMinusBlock",
      "id": 393786,
      "name": "One minus",
      "comments": "",
      "inputs": [
        {
          "name": "input",
          "inputName": "input",
          "targetBlockId": 393039,
          "targetConnectionName": "output"
        }
      ],
      "outputs": [
        {
          "name": "output"
        }
      ]
    },
    {
      "customType": "BABYLON.StepBlock",
      "id": 393039,
      "name": "Step",
      "comments": "",
      "inputs": [
        {
          "name": "value",
          "inputName": "value",
          "targetBlockId": 392081,
          "targetConnectionName": "output"
        },
        {
          "name": "edge",
          "inputName": "edge",
          "targetBlockId": 393284,
          "targetConnectionName": "output"
        }
      ],
      "outputs": [
        {
          "name": "output"
        }
      ]
    },
    {
      "customType": "BABYLON.InputBlock",
      "id": 393284,
      "name": "zero",
      "comments": "",
      "inputs": [],
      "outputs": [
        {
          "name": "output"
        }
      ],
      "type": 1,
      "mode": 0,
      "systemValue": null,
      "animationType": 0,
      "visibleInInspector": false,
      "min": 0,
      "max": 0,
      "isBoolean": false,
      "matrixMode": 0,
      "isConstant": true,
      "groupInInspector": "",
      "valueType": "number",
      "value": 0
    },
    {
      "customType": "BABYLON.MultiplyBlock",
      "id": 394308,
      "name": "Multiply",
      "comments": "",
      "inputs": [
        {
          "name": "left",
          "inputName": "left",
          "targetBlockId": 392081,
          "targetConnectionName": "output"
        },
        {
          "name": "right",
          "inputName": "right",
          "targetBlockId": 393039,
          "targetConnectionName": "output"
        }
      ],
      "outputs": [
        {
          "name": "output"
        }
      ]
    },
    {
      "customType": "BABYLON.StepBlock",
      "id": 391819,
      "name": "Step",
      "comments": "",
      "inputs": [
        {
          "name": "value",
          "inputName": "value",
          "targetBlockId": 391820,
          "targetConnectionName": "output"
        },
        {
          "name": "edge",
          "inputName": "edge",
          "targetBlockId": 391821,
          "targetConnectionName": "output"
        }
      ],
      "outputs": [
        {
          "name": "output"
        }
      ]
    },
    {
      "customType": "BABYLON.InputBlock",
      "id": 391820,
      "name": "reverse",
      "comments": "",
      "inputs": [],
      "outputs": [
        {
          "name": "output"
        }
      ],
      "type": 1,
      "mode": 0,
      "animationType": 0,
      "visibleInInspector": true,
      "min": 0,
      "max": 0,
      "isBoolean": true,
      "matrixMode": 0,
      "isConstant": false,
      "groupInInspector": "mask",
      "valueType": "number",
      "value": 1
    },
    {
      "customType": "BABYLON.InputBlock",
      "id": 391821,
      "name": "Float",
      "comments": "",
      "inputs": [],
      "outputs": [
        {
          "name": "output"
        }
      ],
      "type": 1,
      "mode": 0,
      "animationType": 0,
      "visibleInInspector": false,
      "min": 0,
      "max": 0,
      "isBoolean": false,
      "matrixMode": 0,
      "isConstant": true,
      "groupInInspector": "",
      "valueType": "number",
      "value": 0.5
    },
    {
      "customType": "BABYLON.InputBlock",
      "id": 391822,
      "name": "mask",
      "comments": "",
      "inputs": [],
      "outputs": [
        {
          "name": "output"
        }
      ],
      "type": 1,
      "mode": 0,
      "animationType": 0,
      "visibleInInspector": true,
      "min": -0.1,
      "max": 1.1,
      "isBoolean": false,
      "matrixMode": 0,
      "isConstant": false,
      "groupInInspector": "mask",
      "valueType": "number",
      "value": -0.1
    },
    {
      "customType": "BABYLON.AddBlock",
      "id": 391823,
      "name": "Add",
      "comments": "",
      "inputs": [
        {
          "name": "left",
          "inputName": "left",
          "targetBlockId": 391822,
          "targetConnectionName": "output"
        },
        {
          "name": "right",
          "inputName": "right",
          "targetBlockId": 391824,
          "targetConnectionName": "output"
        }
      ],
      "outputs": [
        {
          "name": "output"
        }
      ]
    },
    {
      "customType": "BABYLON.InputBlock",
      "id": 391824,
      "name": "strokeAlias",
      "comments": "",
      "inputs": [],
      "outputs": [
        {
          "name": "output"
        }
      ],
      "type": 1,
      "mode": 0,
      "animationType": 0,
      "visibleInInspector": true,
      "min": 0,
      "max": 0,
      "isBoolean": false,
      "matrixMode": 0,
      "isConstant": false,
      "groupInInspector": "stroke",
      "valueType": "number",
      "value": 0.01
    },
    {
      "customType": "BABYLON.MultiplyBlock",
      "id": 391825,
      "name": "Multiply",
      "comments": "",
      "inputs": [
        {
          "name": "left",
          "inputName": "left",
          "targetBlockId": 391826,
          "targetConnectionName": "output"
        },
        {
          "name": "right",
          "inputName": "right",
          "targetBlockId": 391836,
          "targetConnectionName": "output"
        }
      ],
      "outputs": [
        {
          "name": "output"
        }
      ]
    },
    {
      "customType": "BABYLON.OneMinusBlock",
      "id": 391826,
      "name": "One minus",
      "comments": "",
      "inputs": [
        {
          "name": "input",
          "inputName": "input",
          "targetBlockId": 391827,
          "targetConnectionName": "output"
        }
      ],
      "outputs": [
        {
          "name": "output"
        }
      ]
    },
    {
      "customType": "BABYLON.SmoothStepBlock",
      "id": 391827,
      "name": "Smooth step",
      "comments": "",
      "inputs": [
        {
          "name": "value",
          "inputName": "value",
          "targetBlockId": 391828,
          "targetConnectionName": "output"
        },
        {
          "name": "edge0",
          "inputName": "edge0",
          "targetBlockId": 391832,
          "targetConnectionName": "output"
        },
        {
          "name": "edge1",
          "inputName": "edge1",
          "targetBlockId": 391835,
          "targetConnectionName": "output"
        }
      ],
      "outputs": [
        {
          "name": "output"
        }
      ]
    },
    {
      "customType": "BABYLON.OneMinusBlock",
      "id": 391828,
      "name": "One minus",
      "comments": "",
      "inputs": [
        {
          "name": "input",
          "inputName": "input",
          "targetBlockId": 391829,
          "targetConnectionName": "output"
        }
      ],
      "outputs": [
        {
          "name": "output"
        }
      ]
    },
    {
      "customType": "BABYLON.OneMinusBlock",
      "id": 391829,
      "name": "polar_y",
      "comments": "polar coordinates Y",
      "inputs": [
        {
          "name": "input",
          "displayName": "input",
          "inputName": "input",
          "targetBlockId": 391830,
          "targetConnectionName": "output"
        }
      ],
      "outputs": [
        {
          "name": "output",
          "displayName": "polar_y"
        }
      ]
    },
    {
      "customType": "BABYLON.LengthBlock",
      "id": 391830,
      "name": "Length",
      "comments": "",
      "inputs": [
        {
          "name": "value",
          "displayName": "value",
          "inputName": "value",
          "targetBlockId": 391831,
          "targetConnectionName": "xy"
        }
      ],
      "outputs": [
        {
          "name": "output",
          "displayName": "output"
        }
      ]
    },
    {
      "customType": "BABYLON.VectorMergerBlock",
      "id": 391831,
      "name": "VectorMerger",
      "comments": "",
      "inputs": [
        {
          "name": "xyz ",
          "displayName": "xyz "
        },
        {
          "name": "xy ",
          "displayName": "xy "
        },
        {
          "name": "x",
          "displayName": "x",
          "inputName": "x",
          "targetBlockId": 391815,
          "targetConnectionName": "output"
        },
        {
          "name": "y",
          "displayName": "y",
          "inputName": "y",
          "targetBlockId": 391809,
          "targetConnectionName": "output"
        },
        {
          "name": "z",
          "displayName": "z"
        },
        {
          "name": "w",
          "displayName": "w"
        }
      ],
      "outputs": [
        {
          "name": "xyzw",
          "displayName": "xyzw"
        },
        {
          "name": "xyz",
          "displayName": "xyz"
        },
        {
          "name": "xy",
          "displayName": "xy"
        }
      ]
    },
    {
      "customType": "BABYLON.AddBlock",
      "id": 391832,
      "name": "Add",
      "comments": "",
      "inputs": [
        {
          "name": "left",
          "inputName": "left",
          "targetBlockId": 391833,
          "targetConnectionName": "output"
        },
        {
          "name": "right",
          "inputName": "right",
          "targetBlockId": 391834,
          "targetConnectionName": "output"
        }
      ],
      "outputs": [
        {
          "name": "output"
        }
      ]
    },
    {
      "customType": "BABYLON.InputBlock",
      "id": 391833,
      "name": "thickness",
      "comments": "",
      "inputs": [],
      "outputs": [
        {
          "name": "output"
        }
      ],
      "type": 1,
      "mode": 0,
      "animationType": 0,
      "visibleInInspector": true,
      "min": 0,
      "max": 0,
      "isBoolean": false,
      "matrixMode": 0,
      "isConstant": false,
      "groupInInspector": "stroke",
      "valueType": "number",
      "value": 0.01
    },
    {
      "customType": "BABYLON.InputBlock",
      "id": 391834,
      "name": "radius",
      "comments": "",
      "inputs": [],
      "outputs": [
        {
          "name": "output"
        }
      ],
      "type": 1,
      "mode": 0,
      "animationType": 0,
      "visibleInInspector": true,
      "min": -0.3,
      "max": 0.9,
      "isBoolean": false,
      "matrixMode": 0,
      "isConstant": false,
      "groupInInspector": "stroke",
      "valueType": "number",
      "value": 0.408
    },
    {
      "customType": "BABYLON.AddBlock",
      "id": 391835,
      "name": "Add",
      "comments": "",
      "inputs": [
        {
          "name": "left",
          "inputName": "left",
          "targetBlockId": 391832,
          "targetConnectionName": "output"
        },
        {
          "name": "right",
          "inputName": "right",
          "targetBlockId": 391824,
          "targetConnectionName": "output"
        }
      ],
      "outputs": [
        {
          "name": "output"
        }
      ]
    },
    {
      "customType": "BABYLON.SmoothStepBlock",
      "id": 391836,
      "name": "Smooth step",
      "comments": "",
      "inputs": [
        {
          "name": "value",
          "inputName": "value",
          "targetBlockId": 391828,
          "targetConnectionName": "output"
        },
        {
          "name": "edge0",
          "inputName": "edge0",
          "targetBlockId": 391837,
          "targetConnectionName": "output"
        },
        {
          "name": "edge1",
          "inputName": "edge1",
          "targetBlockId": 391834,
          "targetConnectionName": "output"
        }
      ],
      "outputs": [
        {
          "name": "output"
        }
      ]
    },
    {
      "customType": "BABYLON.SubtractBlock",
      "id": 391837,
      "name": "Subtract",
      "comments": "",
      "inputs": [
        {
          "name": "left",
          "inputName": "left",
          "targetBlockId": 391834,
          "targetConnectionName": "output"
        },
        {
          "name": "right",
          "inputName": "right",
          "targetBlockId": 391824,
          "targetConnectionName": "output"
        }
      ],
      "outputs": [
        {
          "name": "output"
        }
      ]
    },
    {
      "customType": "BABYLON.LerpBlock",
      "id": 391838,
      "name": "Lerp",
      "comments": "",
      "inputs": [
        {
          "name": "left",
          "inputName": "left",
          "targetBlockId": 391839,
          "targetConnectionName": "output"
        },
        {
          "name": "right",
          "inputName": "right",
          "targetBlockId": 391840,
          "targetConnectionName": "output"
        },
        {
          "name": "gradient",
          "inputName": "gradient",
          "targetBlockId": 391848,
          "targetConnectionName": "output"
        }
      ],
      "outputs": [
        {
          "name": "output"
        }
      ]
    },
    {
      "customType": "BABYLON.InputBlock",
      "id": 391839,
      "name": "notDashed",
      "comments": "",
      "inputs": [],
      "outputs": [
        {
          "name": "output"
        }
      ],
      "type": 1,
      "mode": 0,
      "animationType": 0,
      "visibleInInspector": false,
      "min": 0,
      "max": 0,
      "isBoolean": false,
      "matrixMode": 0,
      "isConstant": true,
      "groupInInspector": "",
      "valueType": "number",
      "value": 1
    },
    {
      "customType": "BABYLON.SmoothStepBlock",
      "id": 391840,
      "name": "Smooth step",
      "comments": "",
      "inputs": [
        {
          "name": "value",
          "inputName": "value",
          "targetBlockId": 391841,
          "targetConnectionName": "output"
        },
        {
          "name": "edge0",
          "inputName": "edge0",
          "targetBlockId": 391845,
          "targetConnectionName": "output"
        },
        {
          "name": "edge1",
          "inputName": "edge1",
          "targetBlockId": 391846,
          "targetConnectionName": "output"
        }
      ],
      "outputs": [
        {
          "name": "output"
        }
      ]
    },
    {
      "customType": "BABYLON.TrigonometryBlock",
      "id": 391841,
      "name": "Sin",
      "comments": "",
      "inputs": [
        {
          "name": "input",
          "inputName": "input",
          "targetBlockId": 391842,
          "targetConnectionName": "output"
        }
      ],
      "outputs": [
        {
          "name": "output"
        }
      ],
      "operation": 1
    },
    {
      "customType": "BABYLON.MultiplyBlock",
      "id": 391842,
      "name": "Multiply",
      "comments": "",
      "inputs": [
        {
          "name": "left",
          "inputName": "left",
          "targetBlockId": 391843,
          "targetConnectionName": "output"
        },
        {
          "name": "right",
          "inputName": "right",
          "targetBlockId": 391844,
          "targetConnectionName": "output"
        }
      ],
      "outputs": [
        {
          "name": "output"
        }
      ]
    },
    {
      "customType": "BABYLON.RemapBlock",
      "id": 391843,
      "name": "Remap",
      "comments": "",
      "inputs": [
        {
          "name": "input",
          "inputName": "input",
          "targetBlockId": 394310,
          "targetConnectionName": "output"
        },
        {
          "name": "sourceMin"
        },
        {
          "name": "sourceMax"
        },
        {
          "name": "targetMin"
        },
        {
          "name": "targetMax"
        }
      ],
      "outputs": [
        {
          "name": "output"
        }
      ],
      "sourceRange": [
        0,
        1
      ],
      "targetRange": [
        0,
        6.28
      ]
    },
    {
      "customType": "BABYLON.InputBlock",
      "id": 391844,
      "name": "dashNumber",
      "comments": "",
      "inputs": [],
      "outputs": [
        {
          "name": "output"
        }
      ],
      "type": 1,
      "mode": 0,
      "animationType": 0,
      "visibleInInspector": true,
      "min": 0,
      "max": 0,
      "isBoolean": false,
      "matrixMode": 0,
      "isConstant": false,
      "groupInInspector": "dash",
      "valueType": "number",
      "value": 50
    },
    {
      "customType": "BABYLON.InputBlock",
      "id": 391845,
      "name": "dashGap",
      "comments": "",
      "inputs": [],
      "outputs": [
        {
          "name": "output"
        }
      ],
      "type": 1,
      "mode": 0,
      "animationType": 0,
      "visibleInInspector": true,
      "min": -1,
      "max": 1,
      "isBoolean": false,
      "matrixMode": 0,
      "isConstant": false,
      "groupInInspector": "dash",
      "valueType": "number",
      "value": 0
    },
    {
      "customType": "BABYLON.AddBlock",
      "id": 391846,
      "name": "Add",
      "comments": "",
      "inputs": [
        {
          "name": "left",
          "inputName": "left",
          "targetBlockId": 391845,
          "targetConnectionName": "output"
        },
        {
          "name": "right",
          "inputName": "right",
          "targetBlockId": 391847,
          "targetConnectionName": "output"
        }
      ],
      "outputs": [
        {
          "name": "output"
        }
      ]
    },
    {
      "customType": "BABYLON.InputBlock",
      "id": 391847,
      "name": "dashAlias",
      "comments": "",
      "inputs": [],
      "outputs": [
        {
          "name": "output"
        }
      ],
      "type": 1,
      "mode": 0,
      "animationType": 0,
      "visibleInInspector": true,
      "min": 0,
      "max": 0,
      "isBoolean": false,
      "matrixMode": 0,
      "isConstant": false,
      "groupInInspector": "dash",
      "valueType": "number",
      "value": 0.5
    },
    {
      "customType": "BABYLON.InputBlock",
      "id": 391848,
      "name": "isDashed",
      "comments": "",
      "inputs": [],
      "outputs": [
        {
          "name": "output"
        }
      ],
      "type": 1,
      "mode": 0,
      "animationType": 0,
      "visibleInInspector": true,
      "min": 0,
      "max": 0,
      "isBoolean": true,
      "matrixMode": 0,
      "isConstant": false,
      "groupInInspector": "dash",
      "valueType": "number",
      "value": 1
    }
  ]
}